JcFile/__init__.py
JcFile-0.0.3.dist-info/METADATA
JcFile-0.0.3.dist-info/WHEEL
JcFile-0.0.3.dist-info/top_level.txt
JcFile-0.0.3.dist-info/RECORD
