Metadata-Version: 2.1
Name: JcFile
Version: 0.0.3
Summary: File I/O library by JavaCommons Technologies
Home-page: https://github.com/javacommons/py-file
Author: JavaCommons Technologies
Author-email: javacommmons@gmail.com
License: MIT
